loveroomb/__init__.py
loveroomb/core.py
loveroomb/log.py
loveroomb/server.py
loveroomb-0.1.1.dist-info/METADATA
loveroomb-0.1.1.dist-info/WHEEL
loveroomb-0.1.1.dist-info/top_level.txt
loveroomb-0.1.1.dist-info/RECORD
