Metadata-Version: 2.4
Name: loveroomb
Version: 0.1.1
Summary: Add your description here
Requires-Python: >=3.10
Requires-Dist: toml==0.10.2
